cblind/__init__.py
cblind/cblind.py
cblind-2.3.2.dist-info/licenses/LICENSE
cblind-2.3.2.dist-info/WHEEL
cblind-2.3.2.dist-info/METADATA
cblind-2.3.2.dist-info/RECORD
