Metadata-Version: 2.4
Name: cblind
Version: 2.3.2
Summary: Colorblind friendly colormaps and color cycles for matplotlib
Author: G. Wafflard-Fernandez
Requires-Python: >=3.10
Classifier: Framework :: Matplotlib
Classifier: Programming Language :: Python :: 3
Classifier: Programming Language :: Python :: 3.10
Classifier: Programming Language :: Python :: 3.11
Classifier: Programming Language :: Python :: 3.12
Classifier: Programming Language :: Python :: 3.13
Classifier: Programming Language :: Python :: 3.14
Classifier: Programming Language :: Python :: Implementation :: CPython
Classifier: Topic :: Scientific/Engineering :: Visualization
License-File: LICENSE
Requires-Dist: matplotlib>=3.5.0
Requires-Dist: cycler>=0.10
Requires-Dist: numpy>=1.21.2
Project-URL: Homepage, https://github.com/la-niche/cblind
